Metadata-Version: 2.1
Name: variousconnector
Version: 1.2
Summary: handy tools to connect the various data sources
Home-page: https://github.com/WeihaoLiTW/variousconnector
Author: Weihao Li
Author-email: weihao.li.tw@gmail.com
License: UNKNOWN
Platform: UNKNOWN
Classifier: Programming Language :: Python :: 3
Classifier: License :: OSI Approved :: MIT License
Classifier: Environment :: Win32 (MS Windows)
Requires-Python: >=3.6
